parallellinear/__init__.py
parallellinear/calculations/CalculationsManager.py
parallellinear/calculations/LinearCalculations.py
parallellinear/calculations/NumpyLinear.py
parallellinear/calculations/ParallelLinear.py
parallellinear/calculations/__init__.py
parallellinear/datatypes/Matrix.py
parallellinear/datatypes/Vector.py
parallellinear/datatypes/__init__.py
ParallelLinear_CraigR8806-0.0.39.dist-info/LICENSE
ParallelLinear_CraigR8806-0.0.39.dist-info/METADATA
ParallelLinear_CraigR8806-0.0.39.dist-info/WHEEL
ParallelLinear_CraigR8806-0.0.39.dist-info/top_level.txt
ParallelLinear_CraigR8806-0.0.39.dist-info/RECORD
